{
  "mdna_found": true,
  "document_score": 0.1,
  "chunks": [
    {
      "score": 0.1,
      "label": "neutral",
      "evidence": [
        "当該年度においては、コロナ禍が当社事業全般に及ぼす影響は限定的でした。",
        "その結果、当連結会計年度の業績は、売上高は、前期に比べ3.2％減少し、営業利益は、前期に比べ0.6％増加し、経常利益は、前期に比べ0.7％増加しました。"
      ]
    },
    {
      "score": 0.1,
      "label": "neutral",
      "evidence": [
        "当期末負債合計額は、前期末に比べ11億８千２百万円増加し、5,073億４千３百万円となりました。",
        "自己資本比率は81.1%から1.0ポイント増加し、82.1%となり、１株当たり純資産額は、前期に比べ462円46銭増加しました。"
      ]
    },
    {
      "score": 0.1,
      "label": "neutral",
      "evidence": [
        "コロナ禍がいつどのように終息するか、世界経済への毀損がどのくらいになるのか、現時点では見通せません。",
        "顧客との意思疎通を密にして、顧客にとって価値ある製品の開発と製品の安定供給に引き続き努めてまいります。"
      ]
    }
  ]
}