{
  "mdna_found": true,
  "document_score": 0.3,
  "chunks": [
    {
      "score": 0.2,
      "label": "neutral",
      "evidence": [
        "当連結会計年度におけるわが国経済は、新型コロナウイルス感染症の影響が長期化する中、依然として厳しい状況にあります。"
      ]
    },
    {
      "score": 0.3,
      "label": "neutral",
      "evidence": [
        "当連結会計年度末の資産合計は、479,419百万円（前期比6.5％増）となりました。"
      ]
    },
    {
      "score": 0.4,
      "label": "positive",
      "evidence": [
        "営業利益41,572百万円(前期比6.7％増)、経常利益42,941百万円(前期比7.2％増)、親会社株主に帰属する当期純利益29,369百万円(前期比13.0％増)となりました。"
      ]
    },
    {
      "score": 0.1,
      "label": "neutral",
      "evidence": [
        "当連結会計年度末における現金及び現金同等物は、前連結会計年度末に比べ2,567百万円減少し、32,936百万円(前期比7.2％減)となりました。"
      ]
    },
    {
      "score": 0.2,
      "label": "neutral",
      "evidence": [
        "当連結会計年度の売上高は563,252百万円となり、前連結会計年度に比べ2,370百万円の増収となりました。"
      ]
    },
    {
      "score": 0.3,
      "label": "neutral",
      "evidence": [
        "当連結会計年度の営業利益は41,572百万円となり、前連結会計年度に比べ2,618百万円の増益となりました。"
      ]
    },
    {
      "score": 0.4,
      "label": "positive",
      "evidence": [
        "当連結会計年度の親会社株主に帰属する当期純利益29,369百万円となり、前連結会計年度に比べ3,374百万円の増益となりました。"
      ]
    },
    {
      "score": 0.3,
      "label": "neutral",
      "evidence": [
        "当連結会計年度の売上高につきましては、563,252百万円(前期比0.4％増)となり、通期目標であった560,000百万円を達成いたしました。"
      ]
    },
    {
      "score": 0.2,
      "label": "neutral",
      "evidence": [
        "日本コムシスグループは、通信事業者の設備投資が減少する中、ＧＩＧＡスクールなどのＩＴソリューション事業や公共事業及び大型太陽光発電設備工事をはじめとする再生可能エネルギー事業などの受注拡大に取り組んでまいりました。"
      ]
    },
    {
      "score": 0.3,
      "label": "neutral",
      "evidence": [
        "サンワコムシスエンジニアリンググループは、ＮＣＣ設備事業において、技術者確保によるシェア拡大とともに、ＩＣＴ活用による費用削減に努めてまいりました。"
      ]
    },
    {
      "score": 0.3,
      "label": "neutral",
      "evidence": [
        "ＴＯＳＹＳグループは、通信事業者の設備投資が減少する中、高度無線環境整備工事やＧＩＧＡスクール等の受注拡大に努め、ワークライフバランスの充実に向けて業務改善や働き方改革に取り組んでまいりました。"
      ]
    },
    {
      "score": 0.3,
      "label": "neutral",
      "evidence": [
        "つうけんグループは、通信事業者からの高度無線環境整備工事及びＧＩＧＡスクールの受注増に加え、大型太陽光発電設備工事やＭ＆Ａ等による業容拡大に取り組んでまいりました。"
      ]
    },
    {
      "score": -0.2,
      "label": "negative",
      "evidence": [
        "ＮＤＳグループは、大型工事案件の減少や工事完成の遅れにより、受注高80,745百万円(前期比3.5％減)、売上高79,213百万円(前期比5.2％減)となり、営業利益も、経費削減等に努めるも減収の影響を補うまでには至らず、3,824百万円(前期比7.7％減)となりました。"
      ]
    },
    {
      "score": 0.3,
      "label": "neutral",
      "evidence": [
        "ＳＹＳＫＥＮグループは、通信事業者からの設備建設工事等の受注確保に加え、九州エリア管内において、高度無線環境整備工事及び大型太陽光発電設備工事、災害復旧工事等の完成、工事管理の効率化による生産性向上に取り組んでまいりました。"
      ]
    },
    {
      "score": 0.4,
      "label": "positive",
      "evidence": [
        "北陸電話工事グループは、通信事業者からの高度無線環境整備工事等の受注拡大に加え、電線共同溝・道路付帯設備工事等の社会インフラ工事及び教育環境整備工事等の受注拡大にも取り組んでまいりました。"
      ]
    },
    {
      "score": 0.3,
      "label": "neutral",
      "evidence": [
        "コムシス情報システムグループは、通信事業者や官公庁及び金融系事業分野の受注拡大に取り組んでまいりました。"
      ]
    },
    {
      "score": 0.2,
      "label": "neutral",
      "evidence": [
        "重要な会計上の見積り及び当該見積りに用いた仮定"
      ]
    },
    {
      "score": 0.1,
      "label": "neutral",
      "evidence": [
        "工事進行基準による収益の計上の基礎となる工事原価総額は、工事契約ごとの実行予算を使用して見積りを行っております。"
      ]
    }
  ]
}