{
  "mdna_found": true,
  "document_score": -0.33,
  "chunks": [
    {
      "score": -0.5,
      "label": "negative",
      "evidence": [
        "連結総資産は7兆4,449億円と、前連結会計年度に比べて6,045億円減少しました。",
        "資本は2兆9,966億円と、前連結会計年度に比べて6,107億円減少しました。"
      ]
    },
    {
      "score": 0.0,
      "label": "neutral",
      "evidence": [
        "営業活動によるキャッシュ・フローは当期4,943億円の収入となりました（前期は4,523億円の収入）。",
        "投資活動によるキャッシュ・フローは当期3,456億円の支出となりました（前期は3,818億円の支出）。"
      ]
    },
    {
      "score": -0.5,
      "label": "negative",
      "evidence": [
        "鉄鋼市況については、世界経済の減速を受けて、自動車生産等消費財の生産が減退した結果、鋼板系品種の需要が減少し、国内外ともに低迷しました。"
      ]
    },
    {
      "score": -1.0,
      "label": "negative",
      "evidence": [
        "連結売上収益は５兆9,215億円（前年同期は６兆1,779億円）、連結事業利益は△2,844億円（前年同期は3,369億円）となりました。"
      ]
    },
    {
      "score": -0.5,
      "label": "negative",
      "evidence": [
        "原料コストの増加と販売価格・品種構成の改善を合わせたマージンは、前期に対して△1,190億円悪化しました。"
      ]
    },
    {
      "score": 0.0,
      "label": "neutral",
      "evidence": [
        "コールケミカル事業は、上期まで堅調に推移してきた黒鉛電極向けニードルコークスの需要が下期には陰りを見せ、第４四半期には新型コロナウイルス感染拡大の影響を受けてより厳しい環境となった結果、490億円（前期は540億円）と前期に対して減少しました。"
      ]
    },
    {
      "score": 0.0,
      "label": "neutral",
      "evidence": [
        "当社グループは、上記資本政策の達成に必要な資金を、主として「稼ぐ力」の維持と向上によって生み出される営業キャッシュ・フローから獲得することに加え、必要に応じて銀行借入や社債の発行による調達も実施しております。"
      ]
    },
    {
      "score": 0.0,
      "label": "neutral",
      "evidence": [
        "フリーキャッシュ・フローの状況に応じて、調達環境、金利条件等を勘案して、最適なタイミングで資金調達面での対応を図ります。"
      ]
    },
    {
      "score": -0.5,
      "label": "negative",
      "evidence": [
        "新型コロナウイルス感染症が当社グループの非金融資産の減損における回収可能価額及び繰延税金資産の回収可能性に与える影響については、規模及び期間は不透明ではありますが、2020年度下期にかけて鋼材需要等が回復すると仮定して見積もっております。"
      ]
    }
  ]
}