{
  "mdna_found": true,
  "document_score": 0.5,
  "chunks": [
    {
      "score": 0.5,
      "label": "positive",
      "evidence": [
        "売上収益は５兆1,083億円（前年度比5,811億円増、12.8％増）と増収になりました。",
        "営業利益は、売上増加による操業度差益や合理化努力により、4,127億円（前年度比821億円増、24.8％増）",
        "親会社の所有者に帰属する当期利益は3,206億円（前年度比629億円増、24.4％増）と増益になりました。"
      ]
    },
    {
      "score": 0.5,
      "label": "positive",
      "evidence": [
        "売上収益は１兆3,228億円（前年度比1,835億円増、16.1％増）と増収、営業利益は、売上増加による操業度差益や合理化努力により、1,367億円（前年度比240億円増、21.3％増）と増益になりました。",
        "長期の成長目標として、2025年度に売上収益７兆円、営業利益率10％の達成を掲げています。"
      ]
    },
    {
      "score": 0.5,
      "label": "positive",
      "evidence": [
        "営業活動により得られた資金は、税引前当期利益の増加（前年度比890億円増）等により、前年度に比べ902億円増加し、5,580億円となりました。",
        "連結会社は、その健全な財務状態、営業活動によるキャッシュ・フローを生み出す能力、連結会社の成長を維持するために将来必要な運転資金及び設備投資資金を調達することが可能と考えています。"
      ]
    }
  ]
}