{
  "mdna_found": true,
  "document_score": 0.3,
  "chunks": [
    {
      "score": 0.2,
      "label": "neutral",
      "evidence": [
        "国内及び海外経済は、新型コロナウイルス感染症による厳しい状況が残る中、ワクチン接種の普及や各国政府が実施する各種施策等の効果もあり、一部に弱さがみられたものの持ち直しの動きが続きました。"
      ]
    },
    {
      "score": 0.1,
      "label": "neutral",
      "evidence": [
        "営業収益は873,239百万円（前年同期比101.7％）、営業利益は223,396百万円（同95.6％）となりました。"
      ]
    },
    {
      "score": 0.0,
      "label": "neutral",
      "evidence": [
        "営業収益は712,282百万円（前年同期比104.0％）、営業損失は8,153百万円（前年同期は17,444百万円の営業損失）となりました。"
      ]
    },
    {
      "score": 0.1,
      "label": "neutral",
      "evidence": [
        "営業収益は194,399百万円（前年同期比97.7％）、営業利益は37,549百万円（同78.1％）となりました。"
      ]
    },
    {
      "score": 0.2,
      "label": "neutral",
      "evidence": [
        "総資産は、前連結会計年度末に比べ1,792,446百万円増の8,739,279百万円となりました。"
      ]
    },
    {
      "score": 0.3,
      "label": "positive",
      "evidence": [
        "営業活動によるキャッシュ・フローは、736,476百万円の収入（前年同期比136.4％）となりました。"
      ]
    },
    {
      "score": 0.4,
      "label": "positive",
      "evidence": [
        "財務活動によるキャッシュ・フローは、937,077百万円の収入（前年同期比135.7％）となりました。"
      ]
    },
    {
      "score": 0.5,
      "label": "positive",
      "evidence": [
        "親会社株主に帰属する当期純利益は、前連結会計年度に比べ31,512百万円増加の210,774百万円となりました。"
      ]
    },
    {
      "score": 0.3,
      "label": "positive",
      "evidence": [
        "親会社株主に帰属する当期純利益の計上による210,774百万円の増加、配当金の支払いによる87,576百万円の減少などにより、前連結会計年度に比べ120,349百万円増加しております。"
      ]
    },
    {
      "score": 0.4,
      "label": "positive",
      "evidence": [
        "持続的に企業価値を向上させるため、資本コストを上回るリターンを拡大するとともに、キャッシュ・フローの創出力を高めることを基本方針としております。"
      ]
    }
  ]
}