{
  "mdna_found": true,
  "document_score": 0.4,
  "chunks": [
    {
      "score": 0.5,
      "label": "positive",
      "evidence": [
        "当連結会計年度は、原油価格が上昇したことにより売上高が増加したことに加え、減損損失が減少したこと等から、連結売上高は9,713億円（前連結会計年度比4.0％増）、経常利益は5,192億円（同34.1％増）、親会社株主に帰属する当期純利益は961億円（同138.1％増）となりました。"
      ]
    },
    {
      "score": 0.3,
      "label": "positive",
      "evidence": [
        "販売数量は減少したものの、油価の上昇により、売上高は前連結会計年度比491億円、8.7％増の6,144億円となり、営業利益は前連結会計年度比1,070億円、35.1％増の4,120億円となりました。"
      ]
    },
    {
      "score": 0.2,
      "label": "neutral",
      "evidence": [
        "当社グループの権益比率ベースの生産量は、原油124.9百万バレル(日量342.2千バレル)、天然ガス253.4十億CF(日量694.2百万CF)、合計172.0百万BOE(日量471.1千BOE)となります。"
      ]
    },
    {
      "score": 0.4,
      "label": "positive",
      "evidence": [
        "当連結会計年度の売上高は9,713億円で、このうち、原油売上高は7,826億円と前連結会計年度の7,102億円と比べ724億円、10.2％の増収"
      ]
    },
    {
      "score": 0.4,
      "label": "positive",
      "evidence": [
        "当連結会計年度末における総資産は4兆7,935億円となり、前連結会計年度末の4兆2,523億円と比較して、5,411億円の増加となりました。"
      ]
    }
  ]
}