{
  "mdna_found": true,
  "document_score": 0.2,
  "chunks": [
    {
      "score": 0.1,
      "label": "neutral",
      "evidence": [
        "当期のわが国経済は、新型コロナウイルスの感染拡大により経済活動全般が大きく制限され、個人消費や輸出を中心に大きく落込み、景気は厳しい状況となりました。"
      ]
    },
    {
      "score": 0.3,
      "label": "positive",
      "evidence": [
        "営業利益は347億29百万円（前年同期比31億42百万円増、9.9％増益）と過去最高を更新し、売上高営業利益率は9.8％（1.5ポイント増）となりました。"
      ]
    },
    {
      "score": 0.2,
      "label": "neutral",
      "evidence": [
        "食品包材用シートおよびその加工品の販売は、テイクアウト需要の増加により概ね堅調に推移しました。"
      ]
    },
    {
      "score": 0.1,
      "label": "neutral",
      "evidence": [
        "当社グループの生産・販売品目は広範囲かつ多種多様であり、同種の製品であっても、その容量、構造、形式等は必ずしも一様ではなく、また受注生産形態をとらない製品がほとんどであるため、セグメントごとに生産規模および受注規模を金額あるいは数量で示すことは行っておりません。"
      ]
    },
    {
      "score": 0.2,
      "label": "neutral",
      "evidence": [
        "営業活動によるキャッシュ・フローは406億10百万円の収入となりましたが、経営計画「Denka Value-Up」における２つの成長戦略である「事業ポートフォリオの変革」と「革新的プロセスの導入」にもとづく積極的な投資による支出をおこない、また株主還元方針にもとづく配当を実施した結果、当連結会計年度末のネット有利子負債残高は前連結会計年度末に比べ71億12百万円増加し1,122億81百万円となりました。"
      ]
    }
  ]
}