{
  "mdna_found": true,
  "document_score": 0.0,
  "chunks": [
    {
      "score": -0.5,
      "label": "negative",
      "evidence": [
        "世界のGDPがマイナスに転じるなど、大変厳しい経済環境でした。",
        "売上高は2兆1,061億円となり前期比456億円の減収、営業利益は1,718億円で前期比55億円の減益、経常利益は1,780億円で前期比60億円の減益となりました。"
      ]
    },
    {
      "score": -0.5,
      "label": "negative",
      "evidence": [
        "主力事業であるアクリロニトリル事業では、販売数量の減少に加えて、市況下落による交易条件の悪化による減益となっています。",
        "衣料市場でも、外出機会の減少に伴う衣服の需要減少により、衣料向け繊維製品の販売量が減少したことを受けて、減収減益となりました。"
      ]
    },
    {
      "score": 0.5,
      "label": "positive",
      "evidence": [
        "医薬事業においては、増収増益となりました。",
        "クリティカルケア事業COVID-19感染拡大の影響による人工呼吸器の特需があり、販売数量が増加したこと等から、増収増益となりました。"
      ]
    },
    {
      "score": 0.0,
      "label": "neutral",
      "evidence": [
        "当期のフリー・キャッシュ・フローは、959億円の収入となりました。",
        "現金及び現金同等物の期末残高は、前期末に比べて115億円増加し2,162億円となりました。"
      ]
    },
    {
      "score": 0.0,
      "label": "neutral",
      "evidence": [
        "当社グループの連結財務諸表は、我が国において一般に公正妥当と認められている会計基準に基づき作成されています。"
      ]
    },
    {
      "score": 0.0,
      "label": "neutral",
      "evidence": [
        "経営者は、繰延税金資産の回収可能性の判断及び前提となる課税所得やタックスプランニングの見積りは適切であると判断しています。"
      ]
    }
  ]
}