{
  "mdna_found": true,
  "document_score": 0.5,
  "chunks": [
    {
      "score": 0.5,
      "label": "positive",
      "evidence": [
        "売上高1,902,124百万円（前連結会計年度1,479,008百万円、前連結会計年度比28.6％増）",
        "営業利益166,775百万円（同111,814百万円、同比49.2％増）",
        "親会社の所有者に帰属する当期利益131,298百万円（同74,681百万円、同比75.8％増）"
      ]
    },
    {
      "score": 0.3,
      "label": "neutral",
      "evidence": [
        "エナジー応用製品セグメント利益は123,212百万円（同147,404百万円、同比16.4％減）",
        "営業活動によって得たキャッシュ・フローは、178,987百万円となり、前連結会計年度比51,868百万円減少しました"
      ]
    },
    {
      "score": 0.4,
      "label": "positive",
      "evidence": [
        "売上高は1兆9,021億円、前連結会計年度比4,231億円、28.6％の増収",
        "営業利益は1,668億円、前連結会計年度比550億円、49.2％の増益"
      ]
    },
    {
      "score": 0.5,
      "label": "positive",
      "evidence": [
        "売上高、営業利益は過去最高を更新しました",
        "受動部品の収益拡大やセンサの黒字化によって、よりバランスの良い収益構造となり収益性も向上しました"
      ]
    },
    {
      "score": 0.2,
      "label": "neutral",
      "evidence": [
        "新型コロナウイルス感染再拡大、地政学的リスクによる世界経済の不確実性等が当社グループの資金繰りに及ぼす影響に備え、流動性資金の拡充や金融機関からの借入金長期化、社債の発行など、対策を講じております"
      ]
    },
    {
      "score": 0.4,
      "label": "positive",
      "evidence": [
        "ＲＯＥは、前連結会計年度の8.5％から3.1ポイント改善し、11.6％となりました",
        "売上増加によるＲＯＳの上昇が寄与しました"
      ]
    },
    {
      "score": 0.5,
      "label": "positive",
      "evidence": [
        "営業利益は773億円、前連結会計年度比約1.9倍の増益",
        "営業利益率も15.3％となり、収益性も大きく向上しました"
      ]
    },
    {
      "score": 0.4,
      "label": "positive",
      "evidence": [
        "センサ応用製品セグメントの売上高は130,769百万円（同81,345百万円、同比60.8％増）",
        "営業利益は通期で32億円の黒字化を達成しました"
      ]
    }
  ]
}