{
  "mdna_found": true,
  "document_score": 0.1,
  "chunks": [
    {
      "score": 0.2,
      "label": "positive",
      "evidence": [
        "収益力向上を達成し、次の成長ステージへの土台を築くことができた。"
      ]
    },
    {
      "score": -0.1,
      "label": "negative",
      "evidence": [
        "EBITは、前年度に比べて1,303億円減少し、5,139億円となった。"
      ]
    },
    {
      "score": 0.1,
      "label": "neutral",
      "evidence": [
        "調整後営業利益は、増収の影響等により、前年度に比べて232億円増加し、1,157億円となった。"
      ]
    },
    {
      "score": 0.0,
      "label": "neutral",
      "evidence": [
        "当社は、運転資金の効率的な管理を通じて、事業活動における資本効率の最適化を図るとともに、グループ内の資金の管理を当社や海外の金融子会社に集中させることを推進しており、グループ内の資金管理の効率改善に努めている。"
      ]
    },
    {
      "score": 0.1,
      "label": "neutral",
      "evidence": [
        "フリー・キャッシュ・フローは、前年度に比べて1,943億円増加し、4,471億円の収入となった。"
      ]
    },
    {
      "score": 0.0,
      "label": "neutral",
      "evidence": [
        "将来予想に関する記述は、当社又は当グループが当有価証券報告書提出日現在において合理的であると判断する一定の前提に基づいており、実際の業績等の結果は見通しと大きく異なることがありえる。"
      ]
    }
  ]
}