{
  "mdna_found": true,
  "document_score": 0.1,
  "chunks": [
    {
      "score": 0.1,
      "label": "neutral",
      "evidence": [
        "当期の業績につきましては、自動車部品事業においてワイヤハーネスの売上が好調に推移するとともに、銅条・高機能材事業や銅箔事業においても品種構成の最適化を進め収益性が大きく改善しました。"
      ]
    },
    {
      "score": 0.2,
      "label": "positive",
      "evidence": [
        "自動車部品事業においてワイヤハーネスが好調に推移したことに加え、銅条・高機能材事業において品種構成の見直しにより収益性が改善したことや、巻線事業においても自動車関連製品が堅調であったことから、業績は好調に推移しました。"
      ]
    },
    {
      "score": 0.1,
      "label": "neutral",
      "evidence": [
        "営業活動によるキャッシュ・フローは、売上の増加や銅価上昇の影響により運転資本が悪化したものの、税金等調整前当期純利益＋358億円、減価償却費＋263億円等により＋465億円（前連結会計年度比＋80億円）となりました。"
      ]
    },
    {
      "score": 0.1,
      "label": "neutral",
      "evidence": [
        "当社グループでは、積極的な設備投資、研究開発の実施等により当面の資金需要は増加していく見込みです。"
      ]
    }
  ]
}