{
  "mdna_found": true,
  "document_score": 0.0,
  "chunks": [
    {
      "score": 0.0,
      "label": "neutral",
      "evidence": [
        "当連結会計年度の実質業務純益は、総経費の増加に加え、投資運用コンサルティング関連の減収を主因とした手数料関連利益が減益となった一方で、実質的な資金関連の損益及び法人関連の非金利収益等の増益により、前年度比67億円増益の2,890億円となりました。"
      ]
    },
    {
      "score": 0.0,
      "label": "neutral",
      "evidence": [
        "資金運用勘定の平均残高は50兆7,231億円、利息は4,893億円、利回りは0.96％となりました。"
      ]
    },
    {
      "score": 0.0,
      "label": "neutral",
      "evidence": [
        "うち譲渡性預金前連結会計年度2,714,3733570.01当連結会計年度2,531,6713290.01"
      ]
    },
    {
      "score": 0.0,
      "label": "neutral",
      "evidence": [
        "資金運用勘定前連結会計年度55,445,2794,528,77250,916,507795,631288,624507,0070.99当連結会計年度54,933,7974,210,65250,723,144699,736210,369489,3660.96"
      ]
    },
    {
      "score": 0.0,
      "label": "neutral",
      "evidence": [
        "国内の役務取引等収益は4,349億円、役務取引等費用は1,441億円となりました。"
      ]
    },
    {
      "score": 0.0,
      "label": "neutral",
      "evidence": [
        "特定取引収益は1,021億円となりました。国内の特定取引収益は1,011億円となりました。"
      ]
    },
    {
      "score": 0.0,
      "label": "neutral",
      "evidence": [
        "信託財産額は、「金融機関の信託業務の兼営等に関する法律」に基づき信託業務を営む連結子会社の信託財産額であります。"
      ]
    },
    {
      "score": 0.0,
      "label": "neutral",
      "evidence": [
        "貸出金1,445,1950.681,543,1600.69有価証券1,253,4650.591,075,1840.48"
      ]
    },
    {
      "score": 0.0,
      "label": "neutral",
      "evidence": [
        "預金合計前連結会計年度26,681,3085,426,594204,33031,903,572当連結会計年度25,852,0905,118,963282,13330,688,920"
      ]
    },
    {
      "score": 0.0,
      "label": "neutral",
      "evidence": [
        "有価証券は、国債の残高が増加したこと等により、前年度末比6,780億円増加し６兆4,375億円となりました。"
      ]
    },
    {
      "score": 0.0,
      "label": "neutral",
      "evidence": [
        "実質的な資金関連損益の増益、法人関連業務における非金利収益の拡大、市場関連収益などの増加により、実質業務純益は前年度比67億円増益の2,890億円となりました。"
      ]
    },
    {
      "score": 0.0,
      "label": "neutral",
      "evidence": [
        "株式等関係損益は、以下を主因に、前年度比264億円増加し、401億円の利益計上となりました。"
      ]
    },
    {
      "score": 0.0,
      "label": "neutral",
      "evidence": [
        "銀行勘定の貸出金は、前年度末比6,776億円増加し29兆7,033億円となりました。"
      ]
    },
    {
      "score": 0.0,
      "label": "neutral",
      "evidence": [
        "銀行勘定の債務者区分毎の引当率につきましては、要管理先債権の非保全部分に対する引当率は12.6％、その他要注意先債権の債権額に対する引当率は7.1％となりました。"
      ]
    },
    {
      "score": 0.0,
      "label": "neutral",
      "evidence": [
        "預金は、前年度末比１兆2,146億円減少し30兆6,889億円となりました。"
      ]
    }
  ]
}