{
  "mdna_found": true,
  "document_score": 0.5,
  "chunks": [
    {
      "score": 0.8,
      "label": "positive",
      "evidence": [
        "売上高は7,629億円(前期比16.4％増)、営業利益は893億円(同43.0％増)",
        "営業利益は前期比で大きく増加し、過去最高となりました"
      ]
    },
    {
      "score": 0.7,
      "label": "positive",
      "evidence": [
        "売上高は8,500億円(当期比11.4％増)、営業利益930億円(同4.1％増)",
        "２期連続で増収増益となり、営業利益は過去最高を更新する見通しです"
      ]
    },
    {
      "score": 0.8,
      "label": "positive",
      "evidence": [
        "売上高は前期比で大きく増加し、過去最高となりました"
      ]
    },
    {
      "score": 0.6,
      "label": "positive",
      "evidence": [
        "売上高の大幅な増加により、営業利益は前期比で大きく増加し、過去最高となりました"
      ]
    },
    {
      "score": 0.3,
      "label": "neutral",
      "evidence": [
        "売上高は前期比で減少しました"
      ]
    },
    {
      "score": 0.2,
      "label": "neutral",
      "evidence": [
        "売上高減少の影響を受けましたが、固定費抑制や付加価値向上に取り組み、営業利益は前期比で大きく増加しました"
      ]
    },
    {
      "score": 0.5,
      "label": "positive",
      "evidence": [
        "売上高は前期比で大きく増加しました",
        "営業利益は前期比で大きく増加しました"
      ]
    },
    {
      "score": 0.4,
      "label": "neutral",
      "evidence": [
        "当年度末の資産の部は、好調な売上による営業債権の増加や部材確保による在庫の増加により前年度末に比べ1,103億円増加"
      ]
    },
    {
      "score": 0.3,
      "label": "neutral",
      "evidence": [
        "ROIC水準10%を下回る9.6%となりました"
      ]
    },
    {
      "score": 0.2,
      "label": "neutral",
      "evidence": [
        "ROICを単純に分解した「ROS」、「投下資本回転率」といった指標では、現場レベルの業務に直接関係しない"
      ]
    }
  ]
}