{
  "mdna_found": true,
  "document_score": 0.3,
  "chunks": [
    {
      "score": 0.2,
      "label": "neutral",
      "evidence": [
        "当社の連結財務諸表はIFRSに基づいて作成されています。",
        "実際の結果がこれらの見積りと異なることもあり得ます。"
      ]
    },
    {
      "score": 0.5,
      "label": "positive",
      "evidence": [
        "親会社の所有者に帰属する当期純利益は、前年度の2,360億円に対し、2,841億円となりました。",
        "基本的１株当たり親会社の所有者に帰属する当期純利益は、前年度の101円20銭に対し、121円83銭となりました。"
      ]
    },
    {
      "score": 0.3,
      "label": "neutral",
      "evidence": [
        "当年度の営業活動により増加したキャッシュ・フローは2,037億円、投資活動により減少したキャッシュ・フローは1,934億円となり、両者を合計したフリーキャッシュ・フローは、103億円となりました。",
        "フリーキャッシュ・フローは、当年度、一時的な法務関連費用の支払いなどはありましたが、運転資本の良化、設備投資の減少および土地売却に伴う収入などにより、前年度と比較して459億円の良化となりました。"
      ]
    },
    {
      "score": 0.2,
      "label": "neutral",
      "evidence": [
        "当社グループの当年度の連結総資産は、前年度末から2,772億円減少し、6兆139億円となりました。",
        "負債は、普通社債の償還などにより前年度末に比べ4,795億円減少し、3兆9,293億円となりました。"
      ]
    }
  ]
}