{
  "mdna_found": true,
  "document_score": 0.3,
  "chunks": [
    {
      "score": 0.1,
      "label": "neutral",
      "evidence": [
        "経営環境を振り返りますと、新型コロナウイルスの感染拡大により2020年に大きく落ち込んだ世界経済は、ワクチン接種の進展、各国の財政・金融政策の効果により回復基調となりました。"
      ]
    },
    {
      "score": 0.2,
      "label": "positive",
      "evidence": [
        "中期経営計画「Make Waves 1.0」において、「顧客・社会との繋がりを強化し、価値創造力を高める」ことを基本戦略として掲げ、４つの重点戦略を進めてきました。"
      ]
    },
    {
      "score": 0.3,
      "label": "positive",
      "evidence": [
        "「新興国の器楽教育普及累計100万人」の目標に対し、累計129万人を達成しました。"
      ]
    },
    {
      "score": 0.1,
      "label": "neutral",
      "evidence": [
        "売上原価率は、前期から0.5ポイント上昇し62.1％となりました。"
      ]
    },
    {
      "score": 0.4,
      "label": "positive",
      "evidence": [
        "親会社の所有者に帰属する当期利益は、前期に対し106億40百万円(40.0％)増加の372億55百万円となりました。"
      ]
    },
    {
      "score": 0.2,
      "label": "neutral",
      "evidence": [
        "当社グループは、製品の性質上、原則として見込生産を行っております。"
      ]
    }
  ]
}